cctxpsa/AIModel.py
cctxpsa/__init__.py
cctxpsa/cctxpsa.py
cctxpsa/report.py
cctxpsa/pcap_extractor/DNSExtractor.py
cctxpsa/pcap_extractor/Extractor.py
cctxpsa/pcap_extractor/FlowBase.py
cctxpsa/pcap_extractor/FlowExtractor.py
cctxpsa/pcap_extractor/HTTPParser.py
cctxpsa/pcap_extractor/ICMPExtractor.py
cctxpsa/pcap_extractor/IMAPParser.py
cctxpsa/pcap_extractor/MyEncoder.py
cctxpsa/pcap_extractor/POP3Parser.py
cctxpsa/pcap_extractor/SMTPParser.py
cctxpsa/pcap_extractor/TCPFlow.py
cctxpsa/pcap_extractor/__init__.py
cctxpsa/pcap_extractor/mail.py
cctxpsa-0.0.5.dist-info/METADATA
cctxpsa-0.0.5.dist-info/WHEEL
cctxpsa-0.0.5.dist-info/entry_points.txt
cctxpsa-0.0.5.dist-info/top_level.txt
cctxpsa-0.0.5.dist-info/zip-safe
cctxpsa-0.0.5.dist-info/RECORD
