Metadata-Version: 2.1
Name: cctxpsa
Version: 0.0.5
Summary: A command line tool for CCTX to analyser pcap and compare with CCTX's observables offline
Home-page: https://github.com/zoeyyyzou/cctx-pcap-safe-analyser
Author: zoeyyy
Author-email: yzou10@uoguelph.ca
License: MIT
Keywords: python cctx pcap cctxpa terminal
Platform: UNKNOWN
Requires-Dist: dpkt
Requires-Dist: progress
Requires-Dist: requests
Requires-Dist: rich
Requires-Dist: scalable-cuckoo-filter
Requires-Dist: sklearn
